django_markwhat/__init__.py
django_markwhat/_version.py
django_markwhat/models.py
django_markwhat/tests.py
django_markwhat/templatetags/__init__.py
django_markwhat/templatetags/markup.py
django_markwhat-2025.5.31.dist-info/licenses/AUTHORS.rst
django_markwhat-2025.5.31.dist-info/licenses/LICENSE
django_markwhat-2025.5.31.dist-info/METADATA
django_markwhat-2025.5.31.dist-info/WHEEL
django_markwhat-2025.5.31.dist-info/top_level.txt
django_markwhat-2025.5.31.dist-info/RECORD
